cmdargparse/__init__.py
cmdargparse/argument.py
cmdargparse/command.py
cmdargparse/custom.py
cmdargparse/field.py
cmdargparse/namespace.py
cmdargparse/parser.py
cmdargparse/unset.py
cmdargparse-0.1.0.dist-info/licenses/LICENSE
cmdargparse-0.1.0.dist-info/METADATA
cmdargparse-0.1.0.dist-info/WHEEL
cmdargparse-0.1.0.dist-info/top_level.txt
cmdargparse-0.1.0.dist-info/RECORD
